otbenchmark/ReliabilityLibrary.py
otbenchmark/SensitivityLibrary.py
otbenchmark/_AxialStressedBeamReliability.py
otbenchmark/_BoreholeSensitivity.py
otbenchmark/_BorgonovoSensitivity.py
otbenchmark/_ConditionalDistribution.py
otbenchmark/_CrossCutDistribution.py
otbenchmark/_CrossCutFunction.py
otbenchmark/_DirichletSensitivity.py
otbenchmark/_DrawEvent.py
otbenchmark/_FORM.py
otbenchmark/_FloodingSensitivity.py
otbenchmark/_FourBranchSerialSystemReliability.py
otbenchmark/_GSobolSensitivity.py
otbenchmark/_GaussianProductSensitivity.py
otbenchmark/_GaussianSumSensitivity.py
otbenchmark/_IshigamiSensitivity.py
otbenchmark/_JanonSensitivityAlgorithm.py
otbenchmark/_LHS.py
otbenchmark/_MorrisSensitivity.py
otbenchmark/_NLOscillatorSensitivity.py
otbenchmark/_OakleyOHaganSensitivity.py
otbenchmark/_ProbabilitySimulationAlgorithmFactory.py
otbenchmark/_ReliabilityBenchmarkMetaAlgorithm.py
otbenchmark/_ReliabilityBenchmarkProblem.py
otbenchmark/_ReliabilityBenchmarkResult.py
otbenchmark/_ReliabilityProblem107.py
otbenchmark/_ReliabilityProblem110.py
otbenchmark/_ReliabilityProblem111.py
otbenchmark/_ReliabilityProblem14.py
otbenchmark/_ReliabilityProblem22.py
otbenchmark/_ReliabilityProblem24.py
otbenchmark/_ReliabilityProblem25.py
otbenchmark/_ReliabilityProblem28.py
otbenchmark/_ReliabilityProblem31.py
otbenchmark/_ReliabilityProblem33.py
otbenchmark/_ReliabilityProblem35.py
otbenchmark/_ReliabilityProblem38.py
otbenchmark/_ReliabilityProblem53.py
otbenchmark/_ReliabilityProblem54.py
otbenchmark/_ReliabilityProblem55.py
otbenchmark/_ReliabilityProblem57.py
otbenchmark/_ReliabilityProblem60.py
otbenchmark/_ReliabilityProblem63.py
otbenchmark/_ReliabilityProblem75.py
otbenchmark/_ReliabilityProblem77.py
otbenchmark/_ReliabilityProblem8.py
otbenchmark/_ReliabilityProblem89.py
otbenchmark/_ReliabilityProblem91.py
otbenchmark/_RminusSReliability.py
otbenchmark/_SORM.py
otbenchmark/_SensitivityBenchmarkMetaAlgorithm.py
otbenchmark/_SensitivityBenchmarkProblem.py
otbenchmark-0.2.1.dist-info/COPYING
otbenchmark-0.2.1.dist-info/COPYING.LESSER
otbenchmark-0.2.1.dist-info/METADATA
otbenchmark-0.2.1.dist-info/WHEEL
otbenchmark-0.2.1.dist-info/top_level.txt
otbenchmark-0.2.1.dist-info/RECORD
