Metadata-Version: 2.1
Name: otbenchmark
Version: 0.2.1
Summary: A benchmark library for OpenTURNS
Home-page: https://github.com/openturns/otbenchmark
Author: Michaël Baudin, Youssef Jebroun,  Elias Fekhari,  Vincent Chabridon
Author-email: michael.baudin@edf.fr
Maintainer: Michaël Baudin
Maintainer-email: Michaël Baudin <michael.baudin@edf.fr>
Keywords: reliability,sensitivity,benchmark
Classifier: Development Status :: 5 - Production/Stable
Classifier: Environment :: Console
Classifier: License :: OSI Approved :: GNU Lesser General Public License v3 or later (LGPLv3+)
Classifier: Intended Audience :: Science/Research
Classifier: Programming Language :: Python :: 3
Classifier: Topic :: Scientific/Engineering
Requires-Python: >=3.8
License-File: COPYING
License-File: COPYING.LESSER
Requires-Dist: matplotlib >=3
Requires-Dist: numpy <2
Requires-Dist: openturns >=1.23
